omnispectrum/__init__.py
omnispectrum/omnispectrum.py
omnispectrum/standard.csv
omnispectrum-0.9.dist-info/LICENSE
omnispectrum-0.9.dist-info/METADATA
omnispectrum-0.9.dist-info/WHEEL
omnispectrum-0.9.dist-info/top_level.txt
omnispectrum-0.9.dist-info/RECORD
